ai2thor/__init__.py
ai2thor/_builds.py
ai2thor/_quality_settings.py
ai2thor/_version.py
ai2thor/build.py
ai2thor/camera.py
ai2thor/controller.py
ai2thor/docker.py
ai2thor/downloader.py
ai2thor/exceptions.py
ai2thor/fifo_server.py
ai2thor/interact.py
ai2thor/mock_real_server.py
ai2thor/offline_controller.py
ai2thor/platform.py
ai2thor/robot_controller.py
ai2thor/server.py
ai2thor/video_controller.py
ai2thor/wsgi_server.py
ai2thor/util/__init__.py
ai2thor/util/depth.py
ai2thor/util/lock.py
ai2thor/util/metrics.py
ai2thor/util/scene_utils.py
ai2thor/util/scene_yaml_edit.py
ai2thor/util/transforms.py
ai2thor/util/trials.py
ai2thor-5.0.0.data/scripts/ai2thor-xorg
ai2thor-5.0.0.dist-info/LICENSE
ai2thor-5.0.0.dist-info/METADATA
ai2thor-5.0.0.dist-info/WHEEL
ai2thor-5.0.0.dist-info/top_level.txt
ai2thor-5.0.0.dist-info/RECORD
