Metadata-Version: 2.1
Name: ai2thor
Version: 5.0.0
Summary: AI2-THOR: A Near Photo-Realistic Interactable Framework for Embodied AI Agents
Home-page: https://github.com/allenai/ai2thor
Author: Allen Institute for AI
Author-email: ai2thor@allenai.org
License: Apache License 2.0
Keywords: AI2-THOR,Allen AI,Python,Reinforcement Learning,Computer Vision,Artificial Intelligence
Platform: UNKNOWN
Classifier: Intended Audience :: Science/Research
Classifier: Development Status :: 5 - Production/Stable
Classifier: License :: OSI Approved :: Apache Software License
Classifier: Topic :: Scientific/Engineering :: Artificial Intelligence
Classifier: Programming Language :: Python
Classifier: Programming Language :: Python :: 3
Classifier: Programming Language :: Python :: 3.5
Classifier: Programming Language :: Python :: 3.6
Classifier: Programming Language :: Python :: 3.7
Classifier: Programming Language :: Python :: 3.8
Classifier: Intended Audience :: Developers
Classifier: Intended Audience :: Education
Classifier: Intended Audience :: Science/Research
Classifier: Operating System :: MacOS
Classifier: Operating System :: Unix
License-File: LICENSE
